slicing/__init__.py
slicing/constant.py
slicing/factory.py
slicing/writer.py
slicing/info/__init__.py
slicing/info/file_info.py
slicing/info/file_info_list.py
slicing/info/file_info_writer.py
slicing/reader/__init__.py
slicing/reader/dump_reader.py
slicing/reader/reader.py
slicing/stmt/__init__.py
slicing/stmt/statement.py
slicing/stmt/condition/__init__.py
slicing/stmt/condition/always_true.py
slicing/stmt/condition/bytes_conditional.py
slicing/stmt/condition/condition.py
slicing/stmt/condition/conditional.py
slicing/stmt/condition/dump_table_byte_condition.py
slicing/stmt/condition/dump_table_condition.py
slicing/stmt/condition/table_operate_conditional.py
slicing/stmt/tokens/__init__.py
slicing/stmt/tokens/alter.py
slicing/stmt/tokens/call.py
slicing/stmt/tokens/create.py
slicing/stmt/tokens/delete.py
slicing/stmt/tokens/drop.py
slicing/stmt/tokens/fr0m.py
slicing/stmt/tokens/function.py
slicing/stmt/tokens/identifier.py
slicing/stmt/tokens/index.py
slicing/stmt/tokens/insert.py
slicing/stmt/tokens/into.py
slicing/stmt/tokens/on.py
slicing/stmt/tokens/procedure.py
slicing/stmt/tokens/table.py
slicing/stmt/tokens/truncate.py
slicing/stmt/tokens/update.py
slicing/stmt/tokens/view.py
slicing/stype/__init__.py
slicing/stype/gz_slice.py
slicing/stype/line_number.py
slicing/stype/slice.py
slicing/stype/sql_slice.py
slicing/stype/state.py
slicing/stype/zip_slice.py
slicing/stype/lines/__init__.py
slicing/stype/lines/end_normal_line.py
slicing/stype/lines/end_procedure_line.py
slicing/stype/lines/ingore_line.py
slicing/stype/lines/line.py
slicing/stype/lines/start_normal_line.py
slicing/stype/lines/start_procedure_line.py
slicing/tests/__init__.py
slicing/tests/big_dump_example.py
slicing/tests/custom_filter_exclude_example.py
slicing/tests/custom_filter_include_example.py
slicing/tests/file_info_example.py
slicing/tests/folder_path.py
slicing/tests/no_filter_example.py
slicing/tests/table_filter_example.py
slicing-1.0.7.dist-info/METADATA
slicing-1.0.7.dist-info/WHEEL
slicing-1.0.7.dist-info/top_level.txt
slicing-1.0.7.dist-info/RECORD
