Metadata-Version: 2.1
Name: slicing
Version: 1.0.7
Summary: SQL dump 切分SQL
Home-page: http://www.xxx.com
Author: thcpc
Author-email: redcpc@163.com
License: UNKNOWN
Project-URL: Bug Tracker, http://www.xxx.com
Platform: UNKNOWN
Classifier: Programming Language :: Python :: 3
Classifier: License :: OSI Approved :: MIT License
Classifier: Operating System :: OS Independent
Requires-Python: >=3.9
Requires-Dist: sqlparse
